linux_tools/__init__.py
linux_tools/bits.py
linux_tools/irqstat.py
linux_tools/netgraph.py
linux_tools/procstat.py
linux_tools/systar.py
linux_tools/table.py
linux_tools/util.py
linux_tools-0.6.0.dist-info/LICENSE
linux_tools-0.6.0.dist-info/METADATA
linux_tools-0.6.0.dist-info/WHEEL
linux_tools-0.6.0.dist-info/entry_points.txt
linux_tools-0.6.0.dist-info/top_level.txt
linux_tools-0.6.0.dist-info/RECORD
