Metadata-Version: 2.1
Name: linux-tools
Version: 0.6.0
Summary: Various command line utilities for Linux
Author-email: Robin Jarry <~rjarry/public-inbox@lists.sr.ht>
License: Apache-2.0
Project-URL: Repository, https://git.sr.ht/~rjarry/linux-tools
Project-URL: Documentation, https://git.sr.ht/~rjarry/linux-tools/tree/main/item/README.md
Project-URL: Issues, https://git.sr.ht/~rjarry/linux-tools#development
Project-URL: Changelog, https://git.sr.ht/~rjarry/linux-tools/log
Classifier: Development Status :: 5 - Production/Stable
Classifier: Environment :: Console
Classifier: Intended Audience :: Developers
Classifier: Topic :: Software Development :: Build Tools
Classifier: License :: OSI Approved :: Apache Software License
Classifier: Operating System :: POSIX :: Linux
Classifier: Programming Language :: Python :: 3
Requires-Python: >=3.9
License-File: LICENSE
